piecewise_regression/__init__.py
piecewise_regression/data_validation.py
piecewise_regression/davies.py
piecewise_regression/main.py
piecewise_regression/model_selection.py
piecewise_regression/r_squared_calc.py
tests/__init__.py
tests/test_data_validation.py
tests/test_fit.py
tests/test_fit_validation.py
tests/test_model_selection.py
tests/test_muggeo.py
tests/test_next_breakpoint.py
tests/test_r_squared.py
piecewise_regression-1.5.0.dist-info/LICENSE.txt
piecewise_regression-1.5.0.dist-info/METADATA
piecewise_regression-1.5.0.dist-info/WHEEL
piecewise_regression-1.5.0.dist-info/top_level.txt
piecewise_regression-1.5.0.dist-info/RECORD
