Metadata-Version: 2.1
Name: piecewise-regression
Version: 1.5.0
Summary: piecewise (segmented) regression in python
Home-page: https://github.com/chasmani/piecewise-regression
Author: Charlie Pilgrim
Author-email: pilgrimcharlie2@gmail.com
License: MIT
Platform: UNKNOWN
Classifier: License :: OSI Approved :: MIT License
Classifier: Programming Language :: Python :: 3
Classifier: Programming Language :: Python :: 3.7
Classifier: Programming Language :: Python :: 3.8
Classifier: Programming Language :: Python :: 3.9
Classifier: Programming Language :: Python :: 3.10
License-File: LICENSE.txt
Requires-Dist: numpy
Requires-Dist: matplotlib
Requires-Dist: scipy
Requires-Dist: statsmodels
